[{"arguments":["clang","-Wno-documentation-unknown-command","-Wno-unknown-warning-option","-Wno-unknown-pragmas","-nostdinc","-nostdinc++","-std=gnu++11","-Wall","-W","-Wextra","-fexceptions","-mthreads","-fsyntax-only","-m64","--target=x86_64-w64-mingw32","-DUNICODE","-D_UNICODE","-DWIN32","-DMINGW_HAS_SECURE_API","-DQT_NO_DEBUG","-DQT_GUI_LIB","-DQT_NETWORK_LIB","-DQT_CORE_LIB","-DQ_CREATOR_RUN","-DQT_ANNOTATE_FUNCTION(x)=__attribute__((annotate(#x)))","-ID:\\QT6\\Tools\\QtCreator\\share\\qtcreator\\cplusplus\\wrappedMingwHeaders","-ID:\\QT6\\Tools\\QtCreator\\share\\qtcreator\\cplusplus\\wrappedQtHeaders","-ID:\\QT6\\Tools\\QtCreator\\share\\qtcreator\\cplusplus\\wrappedQtHeaders\\QtCore","-ID:\\github\\FtpServer\\thief_file","-ID:\\QT6\\5.12.2\\mingw73_64\\include","-ID:\\QT6\\5.12.2\\mingw73_64\\include\\QtGui","-ID:\\QT6\\5.12.2\\mingw73_64\\include\\QtANGLE","-ID:\\QT6\\5.12.2\\mingw73_64\\include\\QtNetwork","-ID:\\QT6\\5.12.2\\mingw73_64\\include\\QtCore","-ID:\\github\\FtpServer\\build-thief_file-Desktop_Qt_5_12_2_MinGW_64_bit-Release\\release","-ID:\\github\\FtpServer\\build-thief_file-Desktop_Qt_5_12_2_MinGW_64_bit-Release","-ID:\\QT6\\5.12.2\\mingw73_64\\mkspecs\\win32-g++","-isystem","D:\\QT6\\Tools\\mingw730_64\\lib\\gcc\\x86_64-w64-mingw32\\7.3.0\\include\\c++","-isystem","D:\\QT6\\Tools\\mingw730_64\\lib\\gcc\\x86_64-w64-mingw32\\7.3.0\\include\\c++\\x86_64-w64-mingw32","-isystem","D:\\QT6\\Tools\\mingw730_64\\lib\\gcc\\x86_64-w64-mingw32\\7.3.0\\include\\c++\\backward","-isystem","D:\\QT6\\Tools\\QtCreator\\bin\\clang\\lib\\clang\\16\\include","-isystem","D:\\QT6\\Tools\\mingw730_64\\x86_64-w64-mingw32\\include","-fmessage-length=0","-fdiagnostics-show-note-include-stack","-fretain-comments-from-system-headers","-fmacro-backtrace-limit=0","-ferror-limit=1000","-x","c++","D:\\github\\FtpServer\\thief_file\\main.cpp"],"directory":"D:/github/FtpServer/build-thief_file-Desktop_Qt_5_12_2_MinGW_64_bit-Release/.qtc_clangd","file":"D:/github/FtpServer/thief_file/main.cpp"},{"arguments":["clang","-Wno-documentation-unknown-command","-Wno-unknown-warning-option","-Wno-unknown-pragmas","-nostdinc","-nostdinc++","-std=gnu++11","-Wall","-W","-Wextra","-fexceptions","-mthreads","-fsyntax-only","-m64","--target=x86_64-w64-mingw32","-DUNICODE","-D_UNICODE","-DWIN32","-DMINGW_HAS_SECURE_API","-DQT_NO_DEBUG","-DQT_GUI_LIB","-DQT_NETWORK_LIB","-DQT_CORE_LIB","-DQ_CREATOR_RUN","-DQT_ANNOTATE_FUNCTION(x)=__attribute__((annotate(#x)))","-ID:\\QT6\\Tools\\QtCreator\\share\\qtcreator\\cplusplus\\wrappedMingwHeaders","-ID:\\QT6\\Tools\\QtCreator\\share\\qtcreator\\cplusplus\\wrappedQtHeaders","-ID:\\QT6\\Tools\\QtCreator\\share\\qtcreator\\cplusplus\\wrappedQtHeaders\\QtCore","-ID:\\github\\FtpServer\\thief_file","-ID:\\QT6\\5.12.2\\mingw73_64\\include","-ID:\\QT6\\5.12.2\\mingw73_64\\include\\QtGui","-ID:\\QT6\\5.12.2\\mingw73_64\\include\\QtANGLE","-ID:\\QT6\\5.12.2\\mingw73_64\\include\\QtNetwork","-ID:\\QT6\\5.12.2\\mingw73_64\\include\\QtCore","-ID:\\github\\FtpServer\\build-thief_file-Desktop_Qt_5_12_2_MinGW_64_bit-Release\\release","-ID:\\github\\FtpServer\\build-thief_file-Desktop_Qt_5_12_2_MinGW_64_bit-Release","-ID:\\QT6\\5.12.2\\mingw73_64\\mkspecs\\win32-g++","-isystem","D:\\QT6\\Tools\\mingw730_64\\lib\\gcc\\x86_64-w64-mingw32\\7.3.0\\include\\c++","-isystem","D:\\QT6\\Tools\\mingw730_64\\lib\\gcc\\x86_64-w64-mingw32\\7.3.0\\include\\c++\\x86_64-w64-mingw32","-isystem","D:\\QT6\\Tools\\mingw730_64\\lib\\gcc\\x86_64-w64-mingw32\\7.3.0\\include\\c++\\backward","-isystem","D:\\QT6\\Tools\\QtCreator\\bin\\clang\\lib\\clang\\16\\include","-isystem","D:\\QT6\\Tools\\mingw730_64\\x86_64-w64-mingw32\\include","-fmessage-length=0","-fdiagnostics-show-note-include-stack","-fretain-comments-from-system-headers","-fmacro-backtrace-limit=0","-ferror-limit=1000","-x","c++","D:\\github\\FtpServer\\thief_file\\fileupload.cpp"],"directory":"D:/github/FtpServer/build-thief_file-Desktop_Qt_5_12_2_MinGW_64_bit-Release/.qtc_clangd","file":"D:/github/FtpServer/thief_file/fileupload.cpp"},{"arguments":["clang","-Wno-documentation-unknown-command","-Wno-unknown-warning-option","-Wno-unknown-pragmas","-nostdinc","-nostdinc++","-std=gnu++11","-Wall","-W","-Wextra","-fexceptions","-mthreads","-fsyntax-only","-m64","--target=x86_64-w64-mingw32","-DUNICODE","-D_UNICODE","-DWIN32","-DMINGW_HAS_SECURE_API","-DQT_NO_DEBUG","-DQT_GUI_LIB","-DQT_NETWORK_LIB","-DQT_CORE_LIB","-DQ_CREATOR_RUN","-DQT_ANNOTATE_FUNCTION(x)=__attribute__((annotate(#x)))","-ID:\\QT6\\Tools\\QtCreator\\share\\qtcreator\\cplusplus\\wrappedMingwHeaders","-ID:\\QT6\\Tools\\QtCreator\\share\\qtcreator\\cplusplus\\wrappedQtHeaders","-ID:\\QT6\\Tools\\QtCreator\\share\\qtcreator\\cplusplus\\wrappedQtHeaders\\QtCore","-ID:\\github\\FtpServer\\thief_file","-ID:\\QT6\\5.12.2\\mingw73_64\\include","-ID:\\QT6\\5.12.2\\mingw73_64\\include\\QtGui","-ID:\\QT6\\5.12.2\\mingw73_64\\include\\QtANGLE","-ID:\\QT6\\5.12.2\\mingw73_64\\include\\QtNetwork","-ID:\\QT6\\5.12.2\\mingw73_64\\include\\QtCore","-ID:\\github\\FtpServer\\build-thief_file-Desktop_Qt_5_12_2_MinGW_64_bit-Release\\release","-ID:\\github\\FtpServer\\build-thief_file-Desktop_Qt_5_12_2_MinGW_64_bit-Release","-ID:\\QT6\\5.12.2\\mingw73_64\\mkspecs\\win32-g++","-isystem","D:\\QT6\\Tools\\mingw730_64\\lib\\gcc\\x86_64-w64-mingw32\\7.3.0\\include\\c++","-isystem","D:\\QT6\\Tools\\mingw730_64\\lib\\gcc\\x86_64-w64-mingw32\\7.3.0\\include\\c++\\x86_64-w64-mingw32","-isystem","D:\\QT6\\Tools\\mingw730_64\\lib\\gcc\\x86_64-w64-mingw32\\7.3.0\\include\\c++\\backward","-isystem","D:\\QT6\\Tools\\QtCreator\\bin\\clang\\lib\\clang\\16\\include","-isystem","D:\\QT6\\Tools\\mingw730_64\\x86_64-w64-mingw32\\include","-fmessage-length=0","-fdiagnostics-show-note-include-stack","-fretain-comments-from-system-headers","-fmacro-backtrace-limit=0","-ferror-limit=1000","-x","c++-header","D:\\github\\FtpServer\\thief_file\\fileupload.h"],"directory":"D:/github/FtpServer/build-thief_file-Desktop_Qt_5_12_2_MinGW_64_bit-Release/.qtc_clangd","file":"D:/github/FtpServer/thief_file/fileupload.h"}]